{
  "name": [
    {
      "id": "efe9",
      "firstName": "Aidar",
      "lastName": "Ferguson",
      "age": "21",
      "state": "RU",
      "city": "Bishkek",
      "street": "Tynystanova, 8A/31",
      "zip": "720085",
      "needed": "surgicalTreatment",
      "diagnosis": "Cardiology",
      "needMoney": "500",
      "leftMoney": 0
    },
    {
      "id": "e0e3",
      "firstName": "Beks",
      "lastName": "Mamytov",
      "age": "15",
      "state": "Kg",
      "city": "Bishkek",
      "street": "Tynystanova, 8A/31",
      "zip": "720085",
      "needed": "targetedTherapy",
      "diagnosis": "SpinalDeformity",
      "needMoney": "5004",
      "leftMoney": 0
    },
    {
      "id": "e21a",
      "firstName": "Dinara",
      "lastName": "Ruslan",
      "age": "34525",
      "state": "En",
      "city": "Bishkek",
      "street": "Tynystanova, 8A/31",
      "zip": "720085",
      "needed": "genomicProfiling",
      "diagnosis": "DeformationsOfSystem",
      "needMoney": 0,
      "leftMoney": 0
    },
    {
      "id": "87f3",
      "firstName": "Aidar",
      "lastName": "Aidarov",
      "age": "24",
      "state": "Ga",
      "city": "Bishkek",
      "street": "Tynystanova, 8A/31",
      "zip": "720085",
      "needed": "surgicalTreatment",
      "diagnosis": "Dota2",
      "needMoney": "6765",
      "leftMoney": 0
    },
    {
      "id": "cc3c",
      "firstName": "Nuris",
      "lastName": "Tashkulov",
      "age": "4",
      "state": "Da",
      "city": "Bishkek",
      "street": "Tynystanova, 8A/31",
      "zip": "720085",
      "needed": "surgicalTreatment",
      "diagnosis": "SpinalDeformity",
      "needMoney": "8888",
      "leftMoney": 0
    },
    {
      "id": "2f7c",
      "firstName": "Diana",
      "lastName": "Com",
      "age": "14",
      "state": "Fr",
      "city": "Bishkek",
      "street": "Tynystanova, 8A/31",
      "zip": "720085",
      "needed": "targetedTherapy",
      "diagnosis": "SpinalDeformity",
      "needMoney": 0,
      "leftMoney": 0
    },
    {
      "id": "321d",
      "firstName": "Байсал",
      "lastName": "Байсал",
      "age": "32",
      "state": "Вавилон",
      "city": "Bishkek",
      "street": "Tynystanova, 8A/31",
      "zip": "720085",
      "needed": "genomicProfiling",
      "diagnosis": "SpinalDeformity",
      "needMoney": "2323423",
      "leftMoney": 32
    },
    {
      "id": "9e35",
      "firstName": "Надира",
      "lastName": "Сулайманова",
      "age": "24",
      "state": "КД",
      "city": "Bishkek",
      "street": "Tynystanova, 8A/31",
      "zip": "720085",
      "needed": "targetedTherapy",
      "diagnosis": "SpinalDeformity",
      "needMoney": "32000",
      "leftMoney": 0,
      "image": {
        "path": "ade.psd"
      }
    },
    {
      "id": "7f74",
      "firstName": "Бектур",
      "lastName": "Маасалиев",
      "age": "20",
      "state": "Фа",
      "city": "Bishkek",
      "street": "Tynystanova, 8A/31",
      "zip": "720085",
      "needed": "surgicalTreatment",
      "diagnosis": "Dota2",
      "needMoney": "32432423",
      "leftMoney": 0,
      "image": {
        "path": "Без имени-6 — копия (2).jpg"
      }
    },
    {
      "id": "91df",
      "firstName": "Ташкул",
      "lastName": "Белеков",
      "age": "34",
      "state": "кпк",
      "city": "Bishkek",
      "street": "Tynystanova, 8A/31",
      "zip": "720085",
      "needed": "targetedTherapy",
      "diagnosis": "Cardiology",
      "needMoney": "4353453",
      "leftMoney": 0,
      "image": {
        "path": "coolestone.png"
      }
    },
    {
      "id": "3186",
      "firstName": "AIdar",
      "lastName": "efwe",
      "age": "342",
      "state": "feew",
      "city": "Bishkek",
      "street": "Tynystanova, 8A/31",
      "zip": "720085",
      "needed": "targetedTherapy",
      "diagnosis": "Dota2",
      "needMoney": "534543534",
      "leftMoney": 34551316,
      "image": {
        "path": "ad.PNG"
      }
    },
    {
      "id": "9977",
      "firstName": "Ая ",
      "lastName": "Шалхар",
      "age": "27",
      "state": "КЗ",
      "city": "Bishkek",
      "street": "Tynystanova, 8A/31",
      "zip": "720085",
      "needed": "targetedTherapy",
      "diagnosis": "Cardiology",
      "needMoney": "4252335",
      "leftMoney": 0,
      "image": {}
    },
    {
      "id": "88a0",
      "firstName": "Ая",
      "lastName": "Шалхар",
      "age": "24",
      "state": "ауца",
      "city": "уацуауц",
      "street": "Tynystanova, 8A/31",
      "zip": "720085",
      "needed": "genomicProfiling",
      "diagnosis": "Cardiology",
      "needMoney": "23432432",
      "leftMoney": 0,
      "image": "https://i.pinimg.com/564x/d7/0a/30/d70a30a33b129eb5d5b6c2de6af20e72.jpg"
    },
    {
      "id": "bbdf",
      "firstName": "Азамат",
      "lastName": "Арсенов",
      "age": "23",
      "state": "Канада",
      "city": "Bishkek",
      "street": "Tynystanova, 8A/31",
      "zip": "720085",
      "needed": "genomicProfiling",
      "diagnosis": "DeformationsOfSystem",
      "needMoney": "4343553",
      "leftMoney": 0,
      "image": "https://i.pinimg.com/564x/f0/37/03/f037039b662a493e706214058ab56e5e.jpg"
    }
  ]
}